Metadata-Version: 2.1
Name: piiwee
Version: 0.4
Summary: A simple cache and permission layer for peewee
Home-page: https://github.com/jianshuo/piiwee
Author: Jianshuo Wang
Author-email: jianshuo@hotmail.com
License: MIT
Keywords: cache permission restful
License-File: LICENSE
